docme/__init__.py
docme/apps.py
docme/decorators.py
docme/docme.py
docme/html_documentation.py
docme/json_documentation.py
docme/output_formats.py
docme/urls.py
docme/views.py
docme/assets/docme.css
docme/assets/feature.html
docme/assets/noscreenshot_step.html
docme/assets/scenario.html
docme/assets/step_horizontal.html
docme/assets/step_vertical.html
docme/static/docme/animate.css
docme/static/docme/auto_tour.js
docme/static/docme/bug.png
docme/static/docme/load.gif
docme/static/docme/question.png
docme/static/docme/images/load.gif
docme/static/docme/js/auto_tour.js
docme/templates/docme/index.html
docme/templates/docme/steps.html
django_docme-0.1.6.dist-info/METADATA
django_docme-0.1.6.dist-info/WHEEL
django_docme-0.1.6.dist-info/top_level.txt
django_docme-0.1.6.dist-info/RECORD
