Metadata-Version: 2.1
Name: django-docme
Version: 0.1.6
Summary: A Django app to generate documentation from behave tests.
Home-page: https://github.com/whanderley/django-docme
Author: Whanderley Souza Freitas
Author-email: whanderley.souza@iff.edu.br
License: BSD-3-Clause  # Example license
Platform: UNKNOWN
Classifier: Environment :: Web Environment
Classifier: Framework :: Django
Classifier: Intended Audience :: Developers
Classifier: License :: OSI Approved :: BSD License
Classifier: Operating System :: OS Independent
Requires-Dist: django-wkhtmltopdf
Requires-Dist: pdfkit
